MANIFEST.in
README.md
requirements.txt
setup.py
django_google_authenticator/__init__.py
django_google_authenticator/admin.py
django_google_authenticator/models.py
django_google_authenticator/settings.py
django_google_authenticator/urls.py
django_google_authenticator/views.py
django_google_authenticator/wsgi.py
django_google_authenticator.egg-info/PKG-INFO
django_google_authenticator.egg-info/SOURCES.txt
django_google_authenticator.egg-info/dependency_links.txt
django_google_authenticator.egg-info/requires.txt
django_google_authenticator.egg-info/top_level.txt
django_google_authenticator/management/__init__.py
django_google_authenticator/management/commands/__init__.py
django_google_authenticator/management/commands/disable_2fa_keys.py
django_google_authenticator/management/commands/enable_2fa_keys.py
django_google_authenticator/migrations/0001_initial.py
django_google_authenticator/migrations/__init__.py
django_google_authenticator/templates/django_google_authenticator/admin/base.html
django_google_authenticator/templates/django_google_authenticator/admin/base_site.html
django_google_authenticator/templates/django_google_authenticator/admin/change_form.html
django_google_authenticator/templates/django_google_authenticator/admin/login.html