Metadata-Version: 1.1
Name: django-google-authenticator
Version: 0.5
Summary: A Django app adding Google Authenticator feature
Home-page: https://github.com/gnosis/django-google-authenticator
Author: Gnosis
Author-email: giacomo.licari@gnosis.pm
License: UNKNOWN
Keywords: google,authenticator,2fa,gnosis
Platform: UNKNOWN
Classifier: Environment :: Web Environment
Classifier: Framework :: Django
Classifier: Intended Audience :: Developers
Classifier: Operating System :: OS Independent
Classifier: Programming Language :: Python
Classifier: Topic :: Internet :: WWW/HTTP
Classifier: Topic :: Internet :: WWW/HTTP :: Dynamic Content
